FoxDotPatterns/__init__.py
FoxDotPatterns/lib/.version
FoxDotPatterns/lib/Buffers.py
FoxDotPatterns/lib/Chords.py
FoxDotPatterns/lib/Constants.py
FoxDotPatterns/lib/Logging.py
FoxDotPatterns/lib/Repeat.py
FoxDotPatterns/lib/Root.py
FoxDotPatterns/lib/Scale.py
FoxDotPatterns/lib/TimeVar.py
FoxDotPatterns/lib/__init__.py
FoxDotPatterns/lib/Patterns/Generators.py
FoxDotPatterns/lib/Patterns/Main.py
FoxDotPatterns/lib/Patterns/Operations.py
FoxDotPatterns/lib/Patterns/PGroups.py
FoxDotPatterns/lib/Patterns/Parse.py
FoxDotPatterns/lib/Patterns/PlayString.py
FoxDotPatterns/lib/Patterns/Sequences.py
FoxDotPatterns/lib/Patterns/Utils.py
FoxDotPatterns/lib/Patterns/__init__.py
FoxDotPatterns/lib/Utils/__init__.py
FoxDotPatterns/snd/_/1/one1.wav
FoxDotPatterns/snd/_/1/one2.wav
FoxDotPatterns/snd/_/2/two1.wav
FoxDotPatterns/snd/_/2/two2.wav
FoxDotPatterns/snd/_/3/three1.wav
FoxDotPatterns/snd/_/3/three2.wav
FoxDotPatterns/snd/_/4/four1.wav
FoxDotPatterns/snd/_/4/four2.wav
FoxDotPatterns/snd/_/ampersand/2_triangle.wav
FoxDotPatterns/snd/_/ampersand/3_triangle.wav
FoxDotPatterns/snd/_/ampersand/4_metal.wav
FoxDotPatterns/snd/_/asterix/0_clap.wav
FoxDotPatterns/snd/_/asterix/1_clap.wav
FoxDotPatterns/snd/_/asterix/2_clap.wav
FoxDotPatterns/snd/_/asterix/4_clap.wav
FoxDotPatterns/snd/_/asterix/5_clap.wav
FoxDotPatterns/snd/_/asterix/6_clap.wav
FoxDotPatterns/snd/_/at/gb_noise (1).wav
FoxDotPatterns/snd/_/at/gb_noise (2).wav
FoxDotPatterns/snd/_/at/gb_noise (3).wav
FoxDotPatterns/snd/_/at/gb_noise (4).wav
FoxDotPatterns/snd/_/at/gb_noise (5).wav
FoxDotPatterns/snd/_/at/gb_noise (6).wav
FoxDotPatterns/snd/_/backslash/0_lazer.wav
FoxDotPatterns/snd/_/backslash/1_lazer.wav
FoxDotPatterns/snd/_/backslash/2_lazer.wav
FoxDotPatterns/snd/_/bar/A#4_light.wav
FoxDotPatterns/snd/_/bar/A3_light.wav
FoxDotPatterns/snd/_/bar/C#4_light.wav
FoxDotPatterns/snd/_/bar/D#3_light.wav
FoxDotPatterns/snd/_/bar/D3_light.wav
FoxDotPatterns/snd/_/bar/G3_light.wav
FoxDotPatterns/snd/_/caret/0.wav
FoxDotPatterns-0.1.0.dist-info/LICENSE
FoxDotPatterns-0.1.0.dist-info/METADATA
FoxDotPatterns-0.1.0.dist-info/WHEEL
FoxDotPatterns-0.1.0.dist-info/top_level.txt
FoxDotPatterns-0.1.0.dist-info/RECORD
