Metadata-Version: 2.1
Name: FoxDotPatterns
Version: 0.1.0
Summary: Small subset of the FoxDot livecoding environment for expressing musical patterns
Home-page: https://github.com/ijc8/FoxDotPatterns
Author: Ian Clester
Author-email: ijc@ijc8.me
License: cc-by-sa-4.0
Platform: UNKNOWN
License-File: LICENSE
